README.rst
setup.py
src/waldur_freeipa/__init__.py
src/waldur_freeipa/admin.py
src/waldur_freeipa/apps.py
src/waldur_freeipa/backend.py
src/waldur_freeipa/extension.py
src/waldur_freeipa/filters.py
src/waldur_freeipa/handlers.py
src/waldur_freeipa/log.py
src/waldur_freeipa/models.py
src/waldur_freeipa/serializers.py
src/waldur_freeipa/tasks.py
src/waldur_freeipa/urls.py
src/waldur_freeipa/utils.py
src/waldur_freeipa/views.py
src/waldur_freeipa.egg-info/PKG-INFO
src/waldur_freeipa.egg-info/SOURCES.txt
src/waldur_freeipa.egg-info/dependency_links.txt
src/waldur_freeipa.egg-info/entry_points.txt
src/waldur_freeipa.egg-info/not-zip-safe
src/waldur_freeipa.egg-info/requires.txt
src/waldur_freeipa.egg-info/top_level.txt
src/waldur_freeipa/migrations/0001_initial.py
src/waldur_freeipa/migrations/0002_decrease_username_length.py
src/waldur_freeipa/migrations/__init__.py